MANIFEST.in
setup.py
piped.contrib.cyclone.egg-info/PKG-INFO
piped.contrib.cyclone.egg-info/SOURCES.txt
piped.contrib.cyclone.egg-info/dependency_links.txt
piped.contrib.cyclone.egg-info/requires.txt
piped.contrib.cyclone.egg-info/top_level.txt
piped/plugins/cyclone_provider.py
piped_cyclone/__init__.py
piped_cyclone/handlers.py
piped_cyclone/providers.py
piped_cyclone/templates/debugger.html
piped_cyclone/test/__init__.py
piped_cyclone/test/test_cyclone.py